[
	{
		"code":"420527101",
		"fullCode":"420527101000",
		"level":3,
		"levelName":"乡级",
		"name":"茅坪镇",
		"parentCode":"420527"
	},
	{
		"code":"420527102",
		"fullCode":"420527102000",
		"level":3,
		"levelName":"乡级",
		"name":"归州镇",
		"parentCode":"420527"
	},
	{
		"code":"420527103",
		"fullCode":"420527103000",
		"level":3,
		"levelName":"乡级",
		"name":"屈原镇",
		"parentCode":"420527"
	},
	{
		"code":"420527104",
		"fullCode":"420527104000",
		"level":3,
		"levelName":"乡级",
		"name":"沙镇溪镇",
		"parentCode":"420527"
	},
	{
		"code":"420527105",
		"fullCode":"420527105000",
		"level":3,
		"levelName":"乡级",
		"name":"两河口镇",
		"parentCode":"420527"
	},
	{
		"code":"420527106",
		"fullCode":"420527106000",
		"level":3,
		"levelName":"乡级",
		"name":"郭家坝镇",
		"parentCode":"420527"
	},
	{
		"code":"420527107",
		"fullCode":"420527107000",
		"level":3,
		"levelName":"乡级",
		"name":"杨林桥镇",
		"parentCode":"420527"
	},
	{
		"code":"420527108",
		"fullCode":"420527108000",
		"level":3,
		"levelName":"乡级",
		"name":"九畹溪镇",
		"parentCode":"420527"
	},
	{
		"code":"420527201",
		"fullCode":"420527201000",
		"level":3,
		"levelName":"乡级",
		"name":"水田坝乡",
		"parentCode":"420527"
	},
	{
		"code":"420527202",
		"fullCode":"420527202000",
		"level":3,
		"levelName":"乡级",
		"name":"泄滩乡",
		"parentCode":"420527"
	},
	{
		"code":"420527203",
		"fullCode":"420527203000",
		"level":3,
		"levelName":"乡级",
		"name":"梅家河乡",
		"parentCode":"420527"
	},
	{
		"code":"420527204",
		"fullCode":"420527204000",
		"level":3,
		"levelName":"乡级",
		"name":"磨坪乡",
		"parentCode":"420527"
	}
]