[
	{
		"code":"330213001",
		"fullCode":"330213001000",
		"level":3,
		"levelName":"乡",
		"name":"锦屏街道",
		"parentCode":"330213"
	},
	{
		"code":"330213002",
		"fullCode":"330213002000",
		"level":3,
		"levelName":"乡",
		"name":"岳林街道",
		"parentCode":"330213"
	},
	{
		"code":"330213003",
		"fullCode":"330213003000",
		"level":3,
		"levelName":"乡",
		"name":"江口街道",
		"parentCode":"330213"
	},
	{
		"code":"330213004",
		"fullCode":"330213004000",
		"level":3,
		"levelName":"乡",
		"name":"西坞街道",
		"parentCode":"330213"
	},
	{
		"code":"330213005",
		"fullCode":"330213005000",
		"level":3,
		"levelName":"乡",
		"name":"萧王庙街道",
		"parentCode":"330213"
	},
	{
		"code":"330213006",
		"fullCode":"330213006000",
		"level":3,
		"levelName":"乡",
		"name":"方桥街道",
		"parentCode":"330213"
	},
	{
		"code":"330213007",
		"fullCode":"330213007000",
		"level":3,
		"levelName":"乡",
		"name":"尚田街道",
		"parentCode":"330213"
	},
	{
		"code":"330213008",
		"fullCode":"330213008000",
		"level":3,
		"levelName":"乡",
		"name":"莼湖街道",
		"parentCode":"330213"
	},
	{
		"code":"330213100",
		"fullCode":"330213100000",
		"level":3,
		"levelName":"乡",
		"name":"溪口镇",
		"parentCode":"330213"
	},
	{
		"code":"330213106",
		"fullCode":"330213106000",
		"level":3,
		"levelName":"乡",
		"name":"裘村镇",
		"parentCode":"330213"
	},
	{
		"code":"330213107",
		"fullCode":"330213107000",
		"level":3,
		"levelName":"乡",
		"name":"大堰镇",
		"parentCode":"330213"
	},
	{
		"code":"330213108",
		"fullCode":"330213108000",
		"level":3,
		"levelName":"乡",
		"name":"松岙镇",
		"parentCode":"330213"
	}
]