[
	{
		"code":"130638203201",
		"fullCode":"130638203201",
		"level":4,
		"levelName":"村",
		"name":"双堂",
		"parentCode":"1306"
	},
	{
		"code":"130638203202",
		"fullCode":"130638203202",
		"level":4,
		"levelName":"村",
		"name":"胡辛庄",
		"parentCode":"1306"
	},
	{
		"code":"130638203203",
		"fullCode":"130638203203",
		"level":4,
		"levelName":"村",
		"name":"谢岗",
		"parentCode":"1306"
	},
	{
		"code":"130638203204",
		"fullCode":"130638203204",
		"level":4,
		"levelName":"村",
		"name":"李岗",
		"parentCode":"1306"
	},
	{
		"code":"130638203205",
		"fullCode":"130638203205",
		"level":4,
		"levelName":"村",
		"name":"冯村",
		"parentCode":"1306"
	},
	{
		"code":"130638203206",
		"fullCode":"130638203206",
		"level":4,
		"levelName":"村",
		"name":"老岗",
		"parentCode":"1306"
	},
	{
		"code":"130638203207",
		"fullCode":"130638203207",
		"level":4,
		"levelName":"村",
		"name":"宫岗",
		"parentCode":"1306"
	},
	{
		"code":"130638203208",
		"fullCode":"130638203208",
		"level":4,
		"levelName":"村",
		"name":"刘庄",
		"parentCode":"1306"
	},
	{
		"code":"130638203209",
		"fullCode":"130638203209",
		"level":4,
		"levelName":"村",
		"name":"陈家柳",
		"parentCode":"1306"
	},
	{
		"code":"130638203210",
		"fullCode":"130638203210",
		"level":4,
		"levelName":"村",
		"name":"贾岗",
		"parentCode":"1306"
	},
	{
		"code":"130638203211",
		"fullCode":"130638203211",
		"level":4,
		"levelName":"村",
		"name":"祁岗",
		"parentCode":"1306"
	},
	{
		"code":"130638203212",
		"fullCode":"130638203212",
		"level":4,
		"levelName":"村",
		"name":"大魏庄",
		"parentCode":"1306"
	},
	{
		"code":"130638203213",
		"fullCode":"130638203213",
		"level":4,
		"levelName":"村",
		"name":"邢庄",
		"parentCode":"1306"
	},
	{
		"code":"130638203214",
		"fullCode":"130638203214",
		"level":4,
		"levelName":"村",
		"name":"乐善庄",
		"parentCode":"1306"
	},
	{
		"code":"130638203215",
		"fullCode":"130638203215",
		"level":4,
		"levelName":"村",
		"name":"东岔河",
		"parentCode":"1306"
	},
	{
		"code":"130638203216",
		"fullCode":"130638203216",
		"level":4,
		"levelName":"村",
		"name":"西岔河",
		"parentCode":"1306"
	},
	{
		"code":"130638203217",
		"fullCode":"130638203217",
		"level":4,
		"levelName":"村",
		"name":"中岔河",
		"parentCode":"1306"
	},
	{
		"code":"130638203218",
		"fullCode":"130638203218",
		"level":4,
		"levelName":"村",
		"name":"徐庄",
		"parentCode":"1306"
	},
	{
		"code":"130638203219",
		"fullCode":"130638203219",
		"level":4,
		"levelName":"村",
		"name":"杜家庄",
		"parentCode":"1306"
	}
]