[
	{
		"code":"220521204001",
		"fullCode":"220521204001",
		"level":4,
		"levelName":"村",
		"name":"金苑社区",
		"parentCode":"2205"
	},
	{
		"code":"220521204200",
		"fullCode":"220521204200",
		"level":4,
		"levelName":"村",
		"name":"金星村",
		"parentCode":"2205"
	},
	{
		"code":"220521204201",
		"fullCode":"220521204201",
		"level":4,
		"levelName":"村",
		"name":"金斗村",
		"parentCode":"2205"
	},
	{
		"code":"220521204202",
		"fullCode":"220521204202",
		"level":4,
		"levelName":"村",
		"name":"北沟村",
		"parentCode":"2205"
	},
	{
		"code":"220521204203",
		"fullCode":"220521204203",
		"level":4,
		"levelName":"村",
		"name":"砬缝村",
		"parentCode":"2205"
	},
	{
		"code":"220521204204",
		"fullCode":"220521204204",
		"level":4,
		"levelName":"村",
		"name":"广信村",
		"parentCode":"2205"
	}
]