[
	{
		"code":"150104006002",
		"fullCode":"150104006002",
		"level":4,
		"levelName":"村",
		"name":"巴彦乌素社区",
		"parentCode":"1501"
	},
	{
		"code":"150104006005",
		"fullCode":"150104006005",
		"level":4,
		"levelName":"村",
		"name":"绿苑社区",
		"parentCode":"1501"
	},
	{
		"code":"150104006006",
		"fullCode":"150104006006",
		"level":4,
		"levelName":"村",
		"name":"兴隆社区",
		"parentCode":"1501"
	},
	{
		"code":"150104006008",
		"fullCode":"150104006008",
		"level":4,
		"levelName":"村",
		"name":"牧科社区",
		"parentCode":"1501"
	},
	{
		"code":"150104006009",
		"fullCode":"150104006009",
		"level":4,
		"levelName":"村",
		"name":"华宇社区",
		"parentCode":"1501"
	},
	{
		"code":"150104006010",
		"fullCode":"150104006010",
		"level":4,
		"levelName":"村",
		"name":"康居社区",
		"parentCode":"1501"
	},
	{
		"code":"150104006011",
		"fullCode":"150104006011",
		"level":4,
		"levelName":"村",
		"name":"正大社区",
		"parentCode":"1501"
	},
	{
		"code":"150104006012",
		"fullCode":"150104006012",
		"level":4,
		"levelName":"村",
		"name":"蓝宇社区",
		"parentCode":"1501"
	},
	{
		"code":"150104006202",
		"fullCode":"150104006202",
		"level":4,
		"levelName":"村",
		"name":"前八里庄",
		"parentCode":"1501"
	},
	{
		"code":"150104006203",
		"fullCode":"150104006203",
		"level":4,
		"levelName":"村",
		"name":"后八里庄",
		"parentCode":"1501"
	},
	{
		"code":"150104006204",
		"fullCode":"150104006204",
		"level":4,
		"levelName":"村",
		"name":"当浪土牧",
		"parentCode":"1501"
	},
	{
		"code":"150104006215",
		"fullCode":"150104006215",
		"level":4,
		"levelName":"村",
		"name":"西瓦窑",
		"parentCode":"1501"
	}
]