[
	{
		"code":"220102004001",
		"fullCode":"220102004001",
		"level":4,
		"levelName":"村",
		"name":"通顺社区",
		"parentCode":"2201"
	},
	{
		"code":"220102004002",
		"fullCode":"220102004002",
		"level":4,
		"levelName":"村",
		"name":"松竹梅社区",
		"parentCode":"2201"
	},
	{
		"code":"220102004003",
		"fullCode":"220102004003",
		"level":4,
		"levelName":"村",
		"name":"永长社区",
		"parentCode":"2201"
	},
	{
		"code":"220102004004",
		"fullCode":"220102004004",
		"level":4,
		"levelName":"村",
		"name":"永春社区",
		"parentCode":"2201"
	},
	{
		"code":"220102004006",
		"fullCode":"220102004006",
		"level":4,
		"levelName":"村",
		"name":"和平社区",
		"parentCode":"2201"
	}
]