[
	{
		"code":"131127101201",
		"fullCode":"131127101201",
		"level":4,
		"levelName":"村",
		"name":"龙华村",
		"parentCode":"1311"
	},
	{
		"code":"131127101202",
		"fullCode":"131127101202",
		"level":4,
		"levelName":"村",
		"name":"吴家窑村",
		"parentCode":"1311"
	},
	{
		"code":"131127101203",
		"fullCode":"131127101203",
		"level":4,
		"levelName":"村",
		"name":"前马堡定村",
		"parentCode":"1311"
	},
	{
		"code":"131127101204",
		"fullCode":"131127101204",
		"level":4,
		"levelName":"村",
		"name":"胡家营村",
		"parentCode":"1311"
	},
	{
		"code":"131127101205",
		"fullCode":"131127101205",
		"level":4,
		"levelName":"村",
		"name":"东单德厢村",
		"parentCode":"1311"
	},
	{
		"code":"131127101206",
		"fullCode":"131127101206",
		"level":4,
		"levelName":"村",
		"name":"张德厢东村",
		"parentCode":"1311"
	},
	{
		"code":"131127101207",
		"fullCode":"131127101207",
		"level":4,
		"levelName":"村",
		"name":"岳王庄村",
		"parentCode":"1311"
	},
	{
		"code":"131127101208",
		"fullCode":"131127101208",
		"level":4,
		"levelName":"村",
		"name":"东野庄村",
		"parentCode":"1311"
	},
	{
		"code":"131127101209",
		"fullCode":"131127101209",
		"level":4,
		"levelName":"村",
		"name":"南文柯村",
		"parentCode":"1311"
	},
	{
		"code":"131127101210",
		"fullCode":"131127101210",
		"level":4,
		"levelName":"村",
		"name":"后马堡定村",
		"parentCode":"1311"
	},
	{
		"code":"131127101211",
		"fullCode":"131127101211",
		"level":4,
		"levelName":"村",
		"name":"南桥村",
		"parentCode":"1311"
	},
	{
		"code":"131127101212",
		"fullCode":"131127101212",
		"level":4,
		"levelName":"村",
		"name":"南高庄村",
		"parentCode":"1311"
	},
	{
		"code":"131127101213",
		"fullCode":"131127101213",
		"level":4,
		"levelName":"村",
		"name":"姜园村",
		"parentCode":"1311"
	},
	{
		"code":"131127101214",
		"fullCode":"131127101214",
		"level":4,
		"levelName":"村",
		"name":"徐堡定村",
		"parentCode":"1311"
	},
	{
		"code":"131127101215",
		"fullCode":"131127101215",
		"level":4,
		"levelName":"村",
		"name":"西野庄村",
		"parentCode":"1311"
	},
	{
		"code":"131127101216",
		"fullCode":"131127101216",
		"level":4,
		"levelName":"村",
		"name":"大冯古庄村",
		"parentCode":"1311"
	},
	{
		"code":"131127101217",
		"fullCode":"131127101217",
		"level":4,
		"levelName":"村",
		"name":"后安村",
		"parentCode":"1311"
	},
	{
		"code":"131127101218",
		"fullCode":"131127101218",
		"level":4,
		"levelName":"村",
		"name":"西苏古庄村",
		"parentCode":"1311"
	},
	{
		"code":"131127101219",
		"fullCode":"131127101219",
		"level":4,
		"levelName":"村",
		"name":"东苏古庄村",
		"parentCode":"1311"
	},
	{
		"code":"131127101220",
		"fullCode":"131127101220",
		"level":4,
		"levelName":"村",
		"name":"邓堡定村",
		"parentCode":"1311"
	},
	{
		"code":"131127101221",
		"fullCode":"131127101221",
		"level":4,
		"levelName":"村",
		"name":"线堡定村",
		"parentCode":"1311"
	},
	{
		"code":"131127101222",
		"fullCode":"131127101222",
		"level":4,
		"levelName":"村",
		"name":"碱场庄村",
		"parentCode":"1311"
	},
	{
		"code":"131127101223",
		"fullCode":"131127101223",
		"level":4,
		"levelName":"村",
		"name":"台辛庄村",
		"parentCode":"1311"
	},
	{
		"code":"131127101224",
		"fullCode":"131127101224",
		"level":4,
		"levelName":"村",
		"name":"北文柯村",
		"parentCode":"1311"
	},
	{
		"code":"131127101225",
		"fullCode":"131127101225",
		"level":4,
		"levelName":"村",
		"name":"后秦旺村",
		"parentCode":"1311"
	},
	{
		"code":"131127101226",
		"fullCode":"131127101226",
		"level":4,
		"levelName":"村",
		"name":"彭村",
		"parentCode":"1311"
	},
	{
		"code":"131127101227",
		"fullCode":"131127101227",
		"level":4,
		"levelName":"村",
		"name":"程庄村",
		"parentCode":"1311"
	},
	{
		"code":"131127101228",
		"fullCode":"131127101228",
		"level":4,
		"levelName":"村",
		"name":"西单德厢村",
		"parentCode":"1311"
	},
	{
		"code":"131127101229",
		"fullCode":"131127101229",
		"level":4,
		"levelName":"村",
		"name":"翟刘庄村",
		"parentCode":"1311"
	},
	{
		"code":"131127101230",
		"fullCode":"131127101230",
		"level":4,
		"levelName":"村",
		"name":"贾吕村",
		"parentCode":"1311"
	},
	{
		"code":"131127101231",
		"fullCode":"131127101231",
		"level":4,
		"levelName":"村",
		"name":"杨躲村",
		"parentCode":"1311"
	},
	{
		"code":"131127101232",
		"fullCode":"131127101232",
		"level":4,
		"levelName":"村",
		"name":"后孙庄村",
		"parentCode":"1311"
	},
	{
		"code":"131127101233",
		"fullCode":"131127101233",
		"level":4,
		"levelName":"村",
		"name":"前孙庄村",
		"parentCode":"1311"
	},
	{
		"code":"131127101234",
		"fullCode":"131127101234",
		"level":4,
		"levelName":"村",
		"name":"张德厢西村",
		"parentCode":"1311"
	},
	{
		"code":"131127101235",
		"fullCode":"131127101235",
		"level":4,
		"levelName":"村",
		"name":"前秦旺村",
		"parentCode":"1311"
	},
	{
		"code":"131127101236",
		"fullCode":"131127101236",
		"level":4,
		"levelName":"村",
		"name":"王德厢村",
		"parentCode":"1311"
	},
	{
		"code":"131127101237",
		"fullCode":"131127101237",
		"level":4,
		"levelName":"村",
		"name":"中秦旺村",
		"parentCode":"1311"
	}
]