[
	{
		"code":"130825112201",
		"fullCode":"130825112201",
		"level":4,
		"levelName":"村",
		"name":"西村",
		"parentCode":"1308"
	},
	{
		"code":"130825112202",
		"fullCode":"130825112202",
		"level":4,
		"levelName":"村",
		"name":"东村",
		"parentCode":"1308"
	},
	{
		"code":"130825112203",
		"fullCode":"130825112203",
		"level":4,
		"levelName":"村",
		"name":"邓厂",
		"parentCode":"1308"
	},
	{
		"code":"130825112204",
		"fullCode":"130825112204",
		"level":4,
		"levelName":"村",
		"name":"樱桃沟门",
		"parentCode":"1308"
	},
	{
		"code":"130825112205",
		"fullCode":"130825112205",
		"level":4,
		"levelName":"村",
		"name":"二沟门",
		"parentCode":"1308"
	},
	{
		"code":"130825112206",
		"fullCode":"130825112206",
		"level":4,
		"levelName":"村",
		"name":"平顶山",
		"parentCode":"1308"
	},
	{
		"code":"130825112207",
		"fullCode":"130825112207",
		"level":4,
		"levelName":"村",
		"name":"烧锅营",
		"parentCode":"1308"
	},
	{
		"code":"130825112208",
		"fullCode":"130825112208",
		"level":4,
		"levelName":"村",
		"name":"营房",
		"parentCode":"1308"
	},
	{
		"code":"130825112209",
		"fullCode":"130825112209",
		"level":4,
		"levelName":"村",
		"name":"梁底",
		"parentCode":"1308"
	},
	{
		"code":"130825112210",
		"fullCode":"130825112210",
		"level":4,
		"levelName":"村",
		"name":"小后沟",
		"parentCode":"1308"
	},
	{
		"code":"130825112211",
		"fullCode":"130825112211",
		"level":4,
		"levelName":"村",
		"name":"上官营",
		"parentCode":"1308"
	},
	{
		"code":"130825112213",
		"fullCode":"130825112213",
		"level":4,
		"levelName":"村",
		"name":"大后沟",
		"parentCode":"1308"
	},
	{
		"code":"130825112214",
		"fullCode":"130825112214",
		"level":4,
		"levelName":"村",
		"name":"石虎沟门",
		"parentCode":"1308"
	},
	{
		"code":"130825112215",
		"fullCode":"130825112215",
		"level":4,
		"levelName":"村",
		"name":"茅吉口",
		"parentCode":"1308"
	},
	{
		"code":"130825112216",
		"fullCode":"130825112216",
		"level":4,
		"levelName":"村",
		"name":"二道湾",
		"parentCode":"1308"
	},
	{
		"code":"130825112217",
		"fullCode":"130825112217",
		"level":4,
		"levelName":"村",
		"name":"岭沟门",
		"parentCode":"1308"
	},
	{
		"code":"130825112218",
		"fullCode":"130825112218",
		"level":4,
		"levelName":"村",
		"name":"栾家湾",
		"parentCode":"1308"
	}
]