[
	{
		"code":"210111005001",
		"fullCode":"210111005001",
		"level":4,
		"levelName":"村",
		"name":"莱茵南郡社区",
		"parentCode":"2101"
	},
	{
		"code":"210111005002",
		"fullCode":"210111005002",
		"level":4,
		"levelName":"村",
		"name":"育红社区",
		"parentCode":"2101"
	},
	{
		"code":"210111005003",
		"fullCode":"210111005003",
		"level":4,
		"levelName":"村",
		"name":"中兴社区",
		"parentCode":"2101"
	},
	{
		"code":"210111005006",
		"fullCode":"210111005006",
		"level":4,
		"levelName":"村",
		"name":"官房社区",
		"parentCode":"2101"
	},
	{
		"code":"210111005007",
		"fullCode":"210111005007",
		"level":4,
		"levelName":"村",
		"name":"铜兴社区",
		"parentCode":"2101"
	},
	{
		"code":"210111005008",
		"fullCode":"210111005008",
		"level":4,
		"levelName":"村",
		"name":"十里锦城社区",
		"parentCode":"2101"
	},
	{
		"code":"210111005009",
		"fullCode":"210111005009",
		"level":4,
		"levelName":"村",
		"name":"施官社区",
		"parentCode":"2101"
	},
	{
		"code":"210111005010",
		"fullCode":"210111005010",
		"level":4,
		"levelName":"村",
		"name":"七家社区",
		"parentCode":"2101"
	},
	{
		"code":"210111005011",
		"fullCode":"210111005011",
		"level":4,
		"levelName":"村",
		"name":"苏家社区",
		"parentCode":"2101"
	},
	{
		"code":"210111005012",
		"fullCode":"210111005012",
		"level":4,
		"levelName":"村",
		"name":"华府丹郡社区",
		"parentCode":"2101"
	},
	{
		"code":"210111005013",
		"fullCode":"210111005013",
		"level":4,
		"levelName":"村",
		"name":"恒大名都社区",
		"parentCode":"2101"
	},
	{
		"code":"210111005014",
		"fullCode":"210111005014",
		"level":4,
		"levelName":"村",
		"name":"奥园新城社区",
		"parentCode":"2101"
	}
]