[
	{
		"code":"140581203201",
		"fullCode":"140581203201",
		"level":4,
		"levelName":"村",
		"name":"原村",
		"parentCode":"1405"
	},
	{
		"code":"140581203202",
		"fullCode":"140581203202",
		"level":4,
		"levelName":"村",
		"name":"狼儿掌",
		"parentCode":"1405"
	},
	{
		"code":"140581203203",
		"fullCode":"140581203203",
		"level":4,
		"levelName":"村",
		"name":"陈庄",
		"parentCode":"1405"
	},
	{
		"code":"140581203204",
		"fullCode":"140581203204",
		"level":4,
		"levelName":"村",
		"name":"常庄",
		"parentCode":"1405"
	},
	{
		"code":"140581203207",
		"fullCode":"140581203207",
		"level":4,
		"levelName":"村",
		"name":"皇王头",
		"parentCode":"1405"
	},
	{
		"code":"140581203208",
		"fullCode":"140581203208",
		"level":4,
		"levelName":"村",
		"name":"下马游",
		"parentCode":"1405"
	},
	{
		"code":"140581203209",
		"fullCode":"140581203209",
		"level":4,
		"levelName":"村",
		"name":"上马游",
		"parentCode":"1405"
	},
	{
		"code":"140581203211",
		"fullCode":"140581203211",
		"level":4,
		"levelName":"村",
		"name":"北山",
		"parentCode":"1405"
	},
	{
		"code":"140581203212",
		"fullCode":"140581203212",
		"level":4,
		"levelName":"村",
		"name":"前河",
		"parentCode":"1405"
	},
	{
		"code":"140581203213",
		"fullCode":"140581203213",
		"level":4,
		"levelName":"村",
		"name":"何李",
		"parentCode":"1405"
	},
	{
		"code":"140581203214",
		"fullCode":"140581203214",
		"level":4,
		"levelName":"村",
		"name":"秦城",
		"parentCode":"1405"
	},
	{
		"code":"140581203215",
		"fullCode":"140581203215",
		"level":4,
		"levelName":"村",
		"name":"冯村",
		"parentCode":"1405"
	},
	{
		"code":"140581203216",
		"fullCode":"140581203216",
		"level":4,
		"levelName":"村",
		"name":"下董峰",
		"parentCode":"1405"
	},
	{
		"code":"140581203218",
		"fullCode":"140581203218",
		"level":4,
		"levelName":"村",
		"name":"窑则头",
		"parentCode":"1405"
	},
	{
		"code":"140581203220",
		"fullCode":"140581203220",
		"level":4,
		"levelName":"村",
		"name":"陈山",
		"parentCode":"1405"
	},
	{
		"code":"140581203223",
		"fullCode":"140581203223",
		"level":4,
		"levelName":"村",
		"name":"良户",
		"parentCode":"1405"
	},
	{
		"code":"140581203224",
		"fullCode":"140581203224",
		"level":4,
		"levelName":"村",
		"name":"章庄",
		"parentCode":"1405"
	},
	{
		"code":"140581203225",
		"fullCode":"140581203225",
		"level":4,
		"levelName":"村",
		"name":"交河",
		"parentCode":"1405"
	},
	{
		"code":"140581203227",
		"fullCode":"140581203227",
		"level":4,
		"levelName":"村",
		"name":"里沟",
		"parentCode":"1405"
	}
]