[
	{
		"code":"130703006001",
		"fullCode":"130703006001",
		"level":4,
		"levelName":"村",
		"name":"南茶坊社区",
		"parentCode":"1307"
	},
	{
		"code":"130703006002",
		"fullCode":"130703006002",
		"level":4,
		"levelName":"村",
		"name":"教场坡社区",
		"parentCode":"1307"
	},
	{
		"code":"130703006003",
		"fullCode":"130703006003",
		"level":4,
		"levelName":"村",
		"name":"西坝岗社区",
		"parentCode":"1307"
	},
	{
		"code":"130703006004",
		"fullCode":"130703006004",
		"level":4,
		"levelName":"村",
		"name":"天宝南苑社区",
		"parentCode":"1307"
	},
	{
		"code":"130703006005",
		"fullCode":"130703006005",
		"level":4,
		"levelName":"村",
		"name":"建设桥社区",
		"parentCode":"1307"
	},
	{
		"code":"130703006006",
		"fullCode":"130703006006",
		"level":4,
		"levelName":"村",
		"name":"宏景嘉苑社区",
		"parentCode":"1307"
	}
]