[
	{
		"code":"140311103202",
		"fullCode":"140311103202",
		"level":4,
		"levelName":"村",
		"name":"龙凤沟",
		"parentCode":"1403"
	},
	{
		"code":"140311103203",
		"fullCode":"140311103203",
		"level":4,
		"levelName":"村",
		"name":"甘河",
		"parentCode":"1403"
	},
	{
		"code":"140311103204",
		"fullCode":"140311103204",
		"level":4,
		"levelName":"村",
		"name":"桃林沟",
		"parentCode":"1403"
	},
	{
		"code":"140311103205",
		"fullCode":"140311103205",
		"level":4,
		"levelName":"村",
		"name":"魏家峪",
		"parentCode":"1403"
	},
	{
		"code":"140311103218",
		"fullCode":"140311103218",
		"level":4,
		"levelName":"村",
		"name":"辛兴",
		"parentCode":"1403"
	},
	{
		"code":"140311103229",
		"fullCode":"140311103229",
		"level":4,
		"levelName":"村",
		"name":"坡头",
		"parentCode":"1403"
	},
	{
		"code":"140311103230",
		"fullCode":"140311103230",
		"level":4,
		"levelName":"村",
		"name":"桑掌",
		"parentCode":"1403"
	},
	{
		"code":"140311103231",
		"fullCode":"140311103231",
		"level":4,
		"levelName":"村",
		"name":"中庄",
		"parentCode":"1403"
	},
	{
		"code":"140311103233",
		"fullCode":"140311103233",
		"level":4,
		"levelName":"村",
		"name":"西上庄",
		"parentCode":"1403"
	},
	{
		"code":"140311103234",
		"fullCode":"140311103234",
		"level":4,
		"levelName":"村",
		"name":"后峪",
		"parentCode":"1403"
	}
]