[
	{
		"code":"210603103200",
		"fullCode":"210603103200",
		"level":4,
		"levelName":"村",
		"name":"萌芽",
		"parentCode":"2106"
	},
	{
		"code":"210603103201",
		"fullCode":"210603103201",
		"level":4,
		"levelName":"村",
		"name":"水源",
		"parentCode":"2106"
	},
	{
		"code":"210603103202",
		"fullCode":"210603103202",
		"level":4,
		"levelName":"村",
		"name":"万宝",
		"parentCode":"2106"
	},
	{
		"code":"210603103203",
		"fullCode":"210603103203",
		"level":4,
		"levelName":"村",
		"name":"石岱",
		"parentCode":"2106"
	},
	{
		"code":"210603103204",
		"fullCode":"210603103204",
		"level":4,
		"levelName":"村",
		"name":"河深沟",
		"parentCode":"2106"
	},
	{
		"code":"210603103205",
		"fullCode":"210603103205",
		"level":4,
		"levelName":"村",
		"name":"复兴",
		"parentCode":"2106"
	},
	{
		"code":"210603103206",
		"fullCode":"210603103206",
		"level":4,
		"levelName":"村",
		"name":"洋子泡",
		"parentCode":"2106"
	},
	{
		"code":"210603103207",
		"fullCode":"210603103207",
		"level":4,
		"levelName":"村",
		"name":"金固",
		"parentCode":"2106"
	},
	{
		"code":"210603103208",
		"fullCode":"210603103208",
		"level":4,
		"levelName":"村",
		"name":"集贤",
		"parentCode":"2106"
	},
	{
		"code":"210603103211",
		"fullCode":"210603103211",
		"level":4,
		"levelName":"村",
		"name":"接梨树",
		"parentCode":"2106"
	},
	{
		"code":"210603103212",
		"fullCode":"210603103212",
		"level":4,
		"levelName":"村",
		"name":"汤池村",
		"parentCode":"2106"
	}
]