[
	{
		"code":"222402003001",
		"fullCode":"222402003001",
		"level":4,
		"levelName":"村",
		"name":"富裕社区",
		"parentCode":"2224"
	},
	{
		"code":"222402003002",
		"fullCode":"222402003002",
		"level":4,
		"levelName":"村",
		"name":"富民社区",
		"parentCode":"2224"
	},
	{
		"code":"222402003003",
		"fullCode":"222402003003",
		"level":4,
		"levelName":"村",
		"name":"富强社区",
		"parentCode":"2224"
	},
	{
		"code":"222402003004",
		"fullCode":"222402003004",
		"level":4,
		"levelName":"村",
		"name":"富华社区",
		"parentCode":"2224"
	}
]