[
	{
		"code":"130132206201",
		"fullCode":"130132206201",
		"level":4,
		"levelName":"村",
		"name":"北正",
		"parentCode":"1301"
	},
	{
		"code":"130132206202",
		"fullCode":"130132206202",
		"level":4,
		"levelName":"村",
		"name":"杨家寨",
		"parentCode":"1301"
	},
	{
		"code":"130132206203",
		"fullCode":"130132206203",
		"level":4,
		"levelName":"村",
		"name":"南正",
		"parentCode":"1301"
	},
	{
		"code":"130132206204",
		"fullCode":"130132206204",
		"level":4,
		"levelName":"村",
		"name":"东台城",
		"parentCode":"1301"
	},
	{
		"code":"130132206205",
		"fullCode":"130132206205",
		"level":4,
		"levelName":"村",
		"name":"西台城",
		"parentCode":"1301"
	},
	{
		"code":"130132206206",
		"fullCode":"130132206206",
		"level":4,
		"levelName":"村",
		"name":"鹿台",
		"parentCode":"1301"
	},
	{
		"code":"130132206207",
		"fullCode":"130132206207",
		"level":4,
		"levelName":"村",
		"name":"窑子庄",
		"parentCode":"1301"
	},
	{
		"code":"130132206208",
		"fullCode":"130132206208",
		"level":4,
		"levelName":"村",
		"name":"时家庄",
		"parentCode":"1301"
	},
	{
		"code":"130132206209",
		"fullCode":"130132206209",
		"level":4,
		"levelName":"村",
		"name":"褚家庄",
		"parentCode":"1301"
	}
]